Python_Cmdr-0.0.0.dist-info/metadata.json
Python_Cmdr-0.0.0.dist-info/RECORD
Python_Cmdr-0.0.0.dist-info/METADATA
Python_Cmdr-0.0.0.dist-info/entry_points.txt
Python_Cmdr-0.0.0.dist-info/DESCRIPTION.rst
Python_Cmdr-0.0.0.dist-info/WHEEL
Python_Cmdr-0.0.0.dist-info/top_level.txt
cmdr/commander.py
cmdr/config.py
cmdr/__init__.py
