Metadata-Version: 2.0
Name: Python-Cmdr
Version: 0.0.0
Summary: A command manager (i.e. Commander) for Python modules and packages.
Home-page: https://github.com/RussellLuo/cmdr
Author: RussellLuo
Author-email: luopeng.he@gmail.com
License: MIT
Keywords: Commander,Command manager,Python
Platform: UNKNOWN
Requires-Dist: click (==4.0)
Requires-Dist: pluginbase (==0.3)
Requires-Dist: python-easyconfig (==0.1.0)
